[
  { "title": "田鎖ブラザーズ",              "sentiment": "positive", "text": "🌟 Filmarks事前clip数2663件！岡田将生×染谷将太の兄弟刑事コンビに期待爆発中" },
  { "title": "GIFT",                        "sentiment": "positive", "text": "👍 日曜劇場に堤真一が帰ってきた！有村架純との共演、本日4/12初回放送！" },
  { "title": "豊臣兄弟！",                   "sentiment": "positive", "text": "🌟 大河ドラマが春も快調。個人視聴率6.9%で民放新ドラマを圧倒中" },
  { "title": "タツキ先生は甘すぎる！",         "sentiment": "positive", "text": "👍 初回放送の反響大！町田啓太×松本穂香の甘々な師弟関係に視聴者メロメロ" },
  { "title": "月夜行路 ―答えは名作の中に―",   "sentiment": "mixed",    "text": "🤔 雰囲気は好きだけど謎解きが弱い。波瑠と麻生久美子のケミは◎だが物足りなさも" },
  { "title": "サバ缶、宇宙へ行く",            "sentiment": "positive", "text": "🌟 北村匠海主演コメディ、明日4/13スタート。clip数2073件で事前buzz急上昇中！" },
  { "title": "リボーン ～最後のヒーロー～",    "sentiment": "positive", "text": "👍 高橋一生がテレ朝火曜21時に！4/14スタート前からファン待機列が形成中" },
  { "title": "時すでにおスシ!?",             "sentiment": "positive", "text": "😍 永作博美の演技が刺さる。等身大の50代女性の再出発に毎話泣かされてます" },
  { "title": "今夜、秘密のキッチンで",        "sentiment": "negative", "text": "👎 設定に共感できない。Filmarks2.5点…ファンタジー要素が完全に浮いていて萎える" },
  { "title": "孤独のグルメ Season11",         "sentiment": "mixed",    "text": "🤔 松重豊の食いっぷりは相変わらず最高。ただ11シーズン目でさすがにマンネリ感も" },
  { "title": "君が死刑になる前に",            "sentiment": "positive", "text": "✨ 深夜枠なのにclip数1953件。加藤清史郎のタイムリープサスペンス、口コミで急拡散中" },
  { "title": "102回目のプロポーズ",           "sentiment": "mixed",    "text": "🤔 1991年名作リメイク。山田涼介の熱演は評価されるも原作比較に賛否両論続出" },
  { "title": "エラー",                        "sentiment": "positive", "text": "🌟 本日4/12テレ朝スタート！吉高由里子主演、SNSで初回反応が好評の嵐" },
  { "title": "ボーダレス～広域移動捜査隊～",   "sentiment": "negative", "text": "😤 土屋太鳳×佐藤勝利なのに脚本が凡庸すぎ。王道刑事ドラマで新鮮味ゼロ" },
  { "title": "LOVED ONE",                    "sentiment": "negative", "text": "😤 アンナチュラルと比べてしまうのが辛い。テーマは重要だがドラマとして面白くない" }
]
